gitlab_ci_tools/__init__.py
gitlab_ci_tools/_version.py
gitlab_ci_tools/last_good_build.py
gitlab_ci_tools-0.1.0.dist-info/DESCRIPTION.rst
gitlab_ci_tools-0.1.0.dist-info/METADATA
gitlab_ci_tools-0.1.0.dist-info/RECORD
gitlab_ci_tools-0.1.0.dist-info/WHEEL
gitlab_ci_tools-0.1.0.dist-info/entry_points.txt
gitlab_ci_tools-0.1.0.dist-info/metadata.json
gitlab_ci_tools-0.1.0.dist-info/top_level.txt
