Metadata-Version: 2.0
Name: gitlab-ci-tools
Version: 0.1.0
Summary: Tools for working inside Gitlab CI
Home-page: https://github.com/jbweston/gitlab-ci-tools
Author: Joseph Weston
Author-email: joseph@weston.cloud
License: BSD 2-Clause
Platform: GNU/Linux
Requires-Dist: python-gitlab
Provides-Extra: dev
Requires-Dist: pep8; extra == 'dev'
Requires-Dist: pylint; extra == 'dev'
